nametag.py
nametag-0.1.0.dist-info/LICENSE.GPLv3
nametag-0.1.0.dist-info/METADATA
nametag-0.1.0.dist-info/WHEEL
nametag-0.1.0.dist-info/entry_points.txt
nametag-0.1.0.dist-info/top_level.txt
nametag-0.1.0.dist-info/RECORD
