Metadata-Version: 2.1
Name: nametag
Version: 0.1.0
Summary: set audio file tags based on file name
Home-page: https://github.com/obfusk/nametag.py
Author: FC Stegerman
Author-email: flx@obfusk.net
License: GPLv3+
Keywords: audio flac mp3 ogg regex tag
Platform: UNKNOWN
Classifier: Development Status :: 4 - Beta
Classifier: Environment :: Console
Classifier: Intended Audience :: End Users/Desktop
Classifier: License :: OSI Approved :: GNU General Public License v3 or later (GPLv3+)
Classifier: Operating System :: POSIX :: Linux
Classifier: Programming Language :: Python :: 3
Classifier: Programming Language :: Python :: 3.8
Classifier: Programming Language :: Python :: 3.9
Classifier: Programming Language :: Python :: 3.10
Classifier: Programming Language :: Python :: Implementation :: CPython
Classifier: Topic :: Multimedia :: Sound/Audio
Classifier: Topic :: Utilities
Requires-Python: >=3.8
License-File: LICENSE.GPLv3
Requires-Dist: click (>=6.0)
Requires-Dist: pytaglib
